tox_backticks.py
tox_backticks-0.2.0.dist-info/LICENSE
tox_backticks-0.2.0.dist-info/METADATA
tox_backticks-0.2.0.dist-info/WHEEL
tox_backticks-0.2.0.dist-info/entry_points.txt
tox_backticks-0.2.0.dist-info/top_level.txt
tox_backticks-0.2.0.dist-info/RECORD
